Metadata-Version: 2.1
Name: sparsezoo-nightly
Version: 1.8.0.20240506
Summary: Neural network model repository for highly sparse and sparse-quantized models with matching sparsification recipes
Home-page: https://github.com/neuralmagic/sparsezoo
Author: Neuralmagic, Inc.
Author-email: support@neuralmagic.com
License: Apache
Keywords: inference,machine learning,neural network,deep learning model,models,computer vision,nlp,pretrained transfer learning,sparsity,pruning,quantization,sparse models,resnet,mobilenet,yolov3
Classifier: Development Status :: 5 - Production/Stable
Classifier: Programming Language :: Python :: 3
Classifier: Programming Language :: Python :: 3 :: Only
Classifier: Programming Language :: Python :: 3.8
Classifier: Programming Language :: Python :: 3.9
Classifier: Programming Language :: Python :: 3.10
Classifier: Programming Language :: Python :: 3.11
Classifier: Intended Audience :: Developers
Classifier: Intended Audience :: Education
Classifier: Intended Audience :: Information Technology
Classifier: Intended Audience :: Science/Research
Classifier: License :: OSI Approved :: Apache Software License
Classifier: Operating System :: POSIX :: Linux
Classifier: Topic :: Scientific/Engineering
Classifier: Topic :: Scientific/Engineering :: Artificial Intelligence
Classifier: Topic :: Scientific/Engineering :: Mathematics
Classifier: Topic :: Software Development
Classifier: Topic :: Software Development :: Libraries :: Python Modules
Requires-Python: >=3.8.0
License-File: LICENSE
License-File: NOTICE
Requires-Dist: numpy >=1.0.0
Requires-Dist: onnx <1.15.0,>=1.5.0
Requires-Dist: pyyaml >=5.1.0
Requires-Dist: requests >=2.0.0
Requires-Dist: tqdm >=4.0.0
Requires-Dist: pydantic <2.8,>=2.0.0
Requires-Dist: click !=8.0.0,>=7.1.2
Requires-Dist: protobuf >=3.12.2
Requires-Dist: pandas >1.3
Requires-Dist: py-machineid >=0.3.0
Requires-Dist: geocoder >=1.38.0
Requires-Dist: onnxruntime >=1.0.0
Provides-Extra: dev
Requires-Dist: beautifulsoup4 ==4.9.3 ; extra == 'dev'
Requires-Dist: black ==22.12.0 ; extra == 'dev'
Requires-Dist: flake8 >=3.8.3 ; extra == 'dev'
Requires-Dist: isort >=5.7.0 ; extra == 'dev'
Requires-Dist: pytest >=6.0.0 ; extra == 'dev'
Requires-Dist: wheel >=0.36.2 ; extra == 'dev'
Requires-Dist: matplotlib >=3.0.0 ; extra == 'dev'
Provides-Extra: docs
Requires-Dist: m2r2 ~=0.2.7 ; extra == 'docs'
Requires-Dist: mistune ==0.8.4 ; extra == 'docs'
Requires-Dist: myst-parser ~=0.14.0 ; extra == 'docs'
Requires-Dist: rinohtype >=0.4.2 ; extra == 'docs'
Requires-Dist: sphinx >=3.4.0 ; extra == 'docs'
Requires-Dist: sphinx-copybutton >=0.3.0 ; extra == 'docs'
Requires-Dist: sphinx-markdown-tables >=0.0.15 ; extra == 'docs'
Requires-Dist: sphinx-multiversion ==0.2.4 ; extra == 'docs'
Requires-Dist: sphinx-rtd-theme ; extra == 'docs'
Provides-Extra: nb
Requires-Dist: ipywidgets >=7.0.0 ; extra == 'nb'
Requires-Dist: jupyter >=1.0.0 ; extra == 'nb'
